[
  {
    "id": "25c520eb-a7e6-42e2-a6a5-a02e9ddfba56",
    "firstname": "Alissa",
    "email": "alissa.lopez@hispeed.ch",
    "password": "Hallo123",
    "username": "alissalopez",
    "mobile": "079 079 79 79"
  },
  {
    "id": "e70c3362-5c9c-4312-b0f5-bc9dc127da8f",
    "firstname": "Alissa",
    "email": "alissa.lopez@hispeed.ch",
    "password": "Hallo123",
    "username": "alissa.lopez",
    "mobile": "079 079 79 79"
  },
  {
    "id": "03212119-fc9a-4e4f-9c83-29ba728a7517",
    "firstname": "A",
    "email": "alissa.lopez@hispeed.ch",
    "password": "Hallo123asdfasdfasdfasdfs",
    "username": "alissa.lopez",
    "mobile": "079 079 79 79"
  },
  {
    "id": "ebbde287-a2a3-4d7f-993e-3df78dedbe72",
    "firstname": "A",
    "email": "alissa.lopez@hispeed.ch",
    "password": "Hallo123",
    "username": "alissa.lopez",
    "mobile": "079 079 79 79"
  },
  {
    "id": "01ea819b-706c-4e33-8de3-d2c62d0815d6",
    "firstname": "Alissa",
    "email": "alissa.lopez@hispeed.ch",
    "password": "Hallo123",
    "username": "alissa.lopez",
    "mobile": "079 079 79 79"
  },
  {
    "id": "181ce55d-8310-4367-a19b-004d5a096a8c",
    "firstname": "Alissa",
    "email": "alissa.lopez@hispeed.ch",
    "password": "Hallo123",
    "username": "alissa.lopez",
    "mobile": "079 079 79 79"
  }
]